locald/__init__.py
locald/cli.py
locald/client.py
locald/compat.py
locald/config.py
locald/server.py
locald/service.py
locald-1.5.data/scripts/locald
locald-1.5.dist-info/LICENSE
locald-1.5.dist-info/METADATA
locald-1.5.dist-info/WHEEL
locald-1.5.dist-info/top_level.txt
locald-1.5.dist-info/RECORD
