Metadata-Version: 2.1
Name: locald
Version: 1.5
Summary: run local services/microservices for development
Home-page: https://github.com/f0rk/locald
Author: Ryan P. Kelly
Author-email: ryan@ryankelly.us
Classifier: Development Status :: 5 - Production/Stable
Classifier: Environment :: Console
Classifier: Intended Audience :: Developers
Classifier: Intended Audience :: System Administrators
Classifier: License :: OSI Approved :: MIT License
Classifier: Operating System :: MacOS :: MacOS X
Classifier: Operating System :: POSIX
Classifier: Programming Language :: Python :: 3
Classifier: Topic :: Software Development
License-File: LICENSE
Requires-Dist: daemonize
Requires-Dist: psutil
